{
"type": "FeatureCollection",
"name": "test",
"crs": { 
    "type": "name", 
    "properties": { 
        "name": "urn:ogc:def:crs:OGC:1.3:CRS84" 
        } 
    },
"features": [{
    "type": "Feature", 
    "properties": {}, 
    "geometry": { 
        "type": "Point", 
        "coordinates": [ -6.153, 55.181 ] 
        } 
    },
    
    { 
    "type": "Feature", 
    "properties": {}, 
    "geometry": { 
        "type": "Point", 
        "coordinates": [ -5.439, 56.451 ] 
        } 
    },
    
    { 
    "type": "Feature", 
    "properties": {}, 
    "geometry": { 
        "type": "Point", 
        "coordinates": [ -6.88, 56.5 ] 
        } 
    },
    ]
}